eemilib/__init__.py
eemilib/main.py
eemilib/core/__init__.py
eemilib/core/model_config.py
eemilib/data/__init__.py
eemilib/data/ag/__init__.py
eemilib/data/ag/emission_energy/__init__.py
eemilib/data/ag/emission_energy/corrected_cleanAg0_100eV_2018.05.30.csv
eemilib/data/ag/emission_energy/corrected_cleanAg0_10eV_2018.05.30.csv
eemilib/data/ag/emission_energy/corrected_cleanAg0_150eV_2018.05.30.csv
eemilib/data/ag/emission_energy/corrected_cleanAg0_20eV_2018.05.30.csv
eemilib/data/ag/emission_energy/corrected_cleanAg0_30eV_2018.05.30.csv
eemilib/data/ag/emission_energy/corrected_cleanAg0_50eV_2018.05.30.csv
eemilib/data/ag/emission_energy/corrected_cleanAg0_70eV_2018.05.30.csv
eemilib/data/cu/__init__.py
eemilib/data/cu/emission_yield/measured_TEEY_Cu_1_eroded.csv
eemilib/data/cu/emission_yield/measured_TEEY_Cu_1_heated.csv
eemilib/data/cu/emission_yield/measured_TEEY_Cu_2_as-received.csv
eemilib/data/cu/emission_yield/measured_TEEY_Cu_2_eroded.csv
eemilib/data/cu/emission_yield/measured_TEEY_Cu_2_heated.csv
eemilib/emission_data/__init__.py
eemilib/emission_data/data_matrix.py
eemilib/emission_data/emission_angle_distribution.py
eemilib/emission_data/emission_data.py
eemilib/emission_data/emission_energy_distribution.py
eemilib/emission_data/emission_yield.py
eemilib/emission_data/helper.py
eemilib/gui/__init__.py
eemilib/gui/file_selection.py
eemilib/gui/gui.py
eemilib/gui/helper.py
eemilib/gui/model_selection.py
eemilib/loader/__init__.py
eemilib/loader/deesse_loader.py
eemilib/loader/helper.py
eemilib/loader/loader.py
eemilib/loader/pandas_loader.py
eemilib/model/__init__.py
eemilib/model/chung_and_everhart.py
eemilib/model/model.py
eemilib/model/parameter.py
eemilib/model/sombrin.py
eemilib/model/vaughan.py
eemilib/plotter/__init__.py
eemilib/plotter/helper.py
eemilib/plotter/pandas.py
eemilib/plotter/plotter.py
eemilib/util/__init__.py
eemilib/util/constants.py
eemilib/util/helper.py
eemilib/util/log_manager.py
eemilib-0.0.15.dist-info/licenses/LICENSE
eemilib-0.0.15.dist-info/METADATA
eemilib-0.0.15.dist-info/WHEEL
eemilib-0.0.15.dist-info/entry_points.txt
eemilib-0.0.15.dist-info/top_level.txt
eemilib-0.0.15.dist-info/RECORD
