Metadata-Version: 2.4
Name: EEmiLib
Version: 0.0.15
Summary: Fit various Electron EMIssion models on experimental data.
Author-email: Adrien Plaçais <placais@lpsc.in2p3.fr>
Project-URL: Documentation, https://adrienplacais.github.io/EEmiLib/
Project-URL: Homepage, https://github.com/AdrienPlacais/EEmiLib
Keywords: electron emission,multipactor
Classifier: Development Status :: 3 - Alpha
Classifier: Intended Audience :: Science/Research
Classifier: License :: OSI Approved :: MIT License
Classifier: Operating System :: OS Independent
Classifier: Programming Language :: Python :: 3.12
Classifier: Topic :: Scientific/Engineering :: Physics
Requires-Python: >=3.12
License-File: LICENSE
Requires-Dist: matplotlib<4,>=3.10.7
Requires-Dist: numpy<3,>=2.3.3
Requires-Dist: pandas<3,>=2.3.3
Requires-Dist: pre-commit<5,>=4
Requires-Dist: PyQt5<6,>=5.15.10
Requires-Dist: scipy<2,>=1.14
Provides-Extra: docs
Requires-Dist: sphinx<9,>=8.2; extra == "docs"
Requires-Dist: myst-parser<5,>=4; extra == "docs"
Requires-Dist: nbsphinx<1,>=0.9.6; extra == "docs"
Requires-Dist: sphinx-rtd-theme<4,>=3; extra == "docs"
Requires-Dist: sphinxcontrib-bibtex<3,>=2.6; extra == "docs"
Requires-Dist: linkify-it-py<3,>=2; extra == "docs"
Provides-Extra: test
Requires-Dist: pytest<9,>=8.3.2; extra == "test"
Dynamic: license-file
